prologix_netfinder/__init__.py
prologix_netfinder/getifaddrs.py
prologix_netfinder/nfcli.py
prologix_netfinder/nfutil.py
prologix_netfinder-0.3.3.dist-info/licenses/LICENSE
prologix_netfinder-0.3.3.dist-info/METADATA
prologix_netfinder-0.3.3.dist-info/WHEEL
prologix_netfinder-0.3.3.dist-info/entry_points.txt
prologix_netfinder-0.3.3.dist-info/top_level.txt
prologix_netfinder-0.3.3.dist-info/RECORD
