Metadata-Version: 2.4
Name: prologix_netfinder
Version: 0.3.3
Summary: Find and configure Prologix GPIB-ETHERNET controllers an a network; modified from original code by Prologix
Maintainer: Justin L. Lanfranchi
License-Expression: MIT AND MIT-0
Project-URL: Homepage, https://github.com/jllanfranchi/prologix_netfinder
Project-URL: Repository, https://github.com/jllanfranchi/prologix_netfinder.git
Project-URL: Issues, https://github.com/jllanfranchi/prologix_netfinder/issues
Keywords: Prologix,GPIB-ETHERNET,Prologix GPIB-ETHERNET,GPIB,Instrument Control
Classifier: Development Status :: 3 - Alpha
Classifier: Environment :: Console
Classifier: Programming Language :: Python :: 3.10
Classifier: Operating System :: POSIX
Classifier: Natural Language :: English
Classifier: Topic :: Scientific/Engineering
Classifier: Topic :: System :: Hardware
Classifier: Typing :: Typed
Requires-Python: >=3.10
License-File: LICENSE
Dynamic: license-file
